ffterm/__init__.py
ffterm/ffterm.cpp
ffterm/image.py
ffterm/lib.py
ffterm/main.py
ffterm/utils.py
ffterm/video.py
ffterm-0.1.5.dist-info/LICENSE
ffterm-0.1.5.dist-info/METADATA
ffterm-0.1.5.dist-info/WHEEL
ffterm-0.1.5.dist-info/entry_points.txt
ffterm-0.1.5.dist-info/top_level.txt
ffterm-0.1.5.dist-info/RECORD
