Metadata-Version: 2.1
Name: ffterm
Version: 0.1.5
Summary: Play media in the terminal.
Home-page: https://github.com/phuang1024/ffterm
Author: Patrick Huang
Author-email: phuang1024@gmail.com
License: UNKNOWN
Platform: UNKNOWN
Classifier: Programming Language :: Python :: 3
Classifier: License :: OSI Approved :: GNU General Public License v3 or later (GPLv3+)
Classifier: Operating System :: OS Independent
Requires-Dist: numpy
Requires-Dist: opencv-python
